{
  "gitSyncId": "67a587eb041d2e7981493273_b464f6c7-c716-4ae7-b620-d2810541274d",
  "id": "Customer messaging_JSObject1.storeInfo",
  "pluginId": "js-plugin",
  "pluginType": "JS",
  "unpublishedAction": {
    "actionConfiguration": {
      "encodeParamsToggle": true,
      "isAsync": true,
      "jsArguments": [],
      "paginationType": "NONE",
      "timeoutInMillisecond": 10000
    },
    "collectionId": "Customer messaging_JSObject1",
    "confirmBeforeExecute": false,
    "datasource": {
      "isAutoGenerated": false,
      "name": "UNUSED_DATASOURCE",
      "pluginId": "js-plugin"
    },
    "dynamicBindingPathList": [
      {
        "key": "body"
      }
    ],
    "executeOnLoad": false,
    "fullyQualifiedName": "JSObject1.storeInfo",
    "name": "storeInfo",
    "pageId": "Customer messaging",
    "userSetOnLoad": false
  }
}